README.md
setup.py
jwt_flask_ext/__init__.py
jwt_flask_ext/auth.py
jwt_flask_ext.egg-info/PKG-INFO
jwt_flask_ext.egg-info/SOURCES.txt
jwt_flask_ext.egg-info/dependency_links.txt
jwt_flask_ext.egg-info/top_level.txt