Metadata-Version: 2.1
Name: jwt_flask_ext
Version: 0.0.2
Summary: Provide an  easy way to handle authentication(login with jwt generated, token required decorator) in flask applications
Author: Eteil Junior Djoumatchoua
